xgbxml/__init__.py
xgbxml/gbxml_functions.py
xgbxml/gbxml_xsd_functions.py
xgbxml/geometry_functions.py
xgbxml/render_functions.py
xgbxml/xgbxml.py
xgbxml/xml_functions.py
xgbxml/xsd_functions.py
xgbxml/auto/__init__.py
xgbxml/auto/_generate_doc_pages.py
xgbxml/auto/_generate_gbElements.py
xgbxml/auto/gbElements_0_32.py
xgbxml/auto/gbElements_0_33.py
xgbxml/auto/gbElements_0_34.py
xgbxml/auto/gbElements_0_35.py
xgbxml/auto/gbElements_0_36.py
xgbxml/auto/gbElements_0_37.py
xgbxml/auto/gbElements_5_00.py
xgbxml/auto/gbElements_5_01.py
xgbxml/auto/gbElements_5_10.py
xgbxml/auto/gbElements_5_11.py
xgbxml/auto/gbElements_5_12.py
xgbxml/auto/gbElements_6_01.py
xgbxml/schema_dicts/__init__.py
xgbxml/schema_dicts/_generate_dicts.py
xgbxml/schemas/GreenBuildingXML_Ver0.32.xsd
xgbxml/schemas/GreenBuildingXML_Ver0.33.xsd
xgbxml/schemas/GreenBuildingXML_Ver0.34.xsd
xgbxml/schemas/GreenBuildingXML_Ver0.35.xsd
xgbxml/schemas/GreenBuildingXML_Ver0.36.xsd
xgbxml/schemas/GreenBuildingXML_Ver0.37.xsd
xgbxml/schemas/GreenBuildingXML_Ver5.00.xsd
xgbxml/schemas/GreenBuildingXML_Ver5.01.xsd
xgbxml/schemas/GreenBuildingXML_Ver5.10.xsd
xgbxml/schemas/GreenBuildingXML_Ver5.11.xsd
xgbxml/schemas/GreenBuildingXML_Ver5.12.xsd
xgbxml/schemas/GreenBuildingXML_Ver6.01.xsd
xgbxml/schemas/__init__.py
xgbxml-0.0.10.dist-info/LICENSE
xgbxml-0.0.10.dist-info/METADATA
xgbxml-0.0.10.dist-info/WHEEL
xgbxml-0.0.10.dist-info/top_level.txt
xgbxml-0.0.10.dist-info/RECORD
